nemo_evaluator/__init__.py
nemo_evaluator/package_info.py
nemo_evaluator/adapters/__init__.py
nemo_evaluator/adapters/adapter_config.py
nemo_evaluator/adapters/decorators.py
nemo_evaluator/adapters/pipeline.py
nemo_evaluator/adapters/registry.py
nemo_evaluator/adapters/server.py
nemo_evaluator/adapters/types.py
nemo_evaluator/adapters/caching/__init__.py
nemo_evaluator/adapters/caching/diskcaching.py
nemo_evaluator/adapters/interceptors/__init__.py
nemo_evaluator/adapters/interceptors/caching_interceptor.py
nemo_evaluator/adapters/interceptors/endpoint_interceptor.py
nemo_evaluator/adapters/interceptors/logging_interceptor.py
nemo_evaluator/adapters/interceptors/payload_modifier_interceptor.py
nemo_evaluator/adapters/interceptors/progress_tracking_interceptor.py
nemo_evaluator/adapters/interceptors/raise_client_error_interceptor.py
nemo_evaluator/adapters/interceptors/reasoning_interceptor.py
nemo_evaluator/adapters/interceptors/response_stats_interceptor.py
nemo_evaluator/adapters/interceptors/system_message_interceptor.py
nemo_evaluator/adapters/reports/__init__.py
nemo_evaluator/adapters/reports/post_eval_report_hook.py
nemo_evaluator/adapters/reports/templates/__init__.py
nemo_evaluator/adapters/reports/templates/simple_template.py
nemo_evaluator/api/__init__.py
nemo_evaluator/api/api_dataclasses.py
nemo_evaluator/cli/__init__.py
nemo_evaluator/cli/example.py
nemo_evaluator/client/__init__.py
nemo_evaluator/client/adapter_transport.py
nemo_evaluator/client/client.py
nemo_evaluator/core/__init__.py
nemo_evaluator/core/entrypoint.py
nemo_evaluator/core/evaluate.py
nemo_evaluator/core/input.py
nemo_evaluator/core/resources.py
nemo_evaluator/core/utils.py
nemo_evaluator/logging/__init__.py
nemo_evaluator/logging/config.py
nemo_evaluator/logging/context.py
nemo_evaluator/logging/utils.py
nemo_evaluator/resources/framework_tpl.yml
nemo_evaluator/resources/init_tpl.py
nemo_evaluator/resources/output_tpl.py
nemo_evaluator/sandbox/__init__.py
nemo_evaluator-0.1.65.dist-info/licenses/LICENSE
nemo_evaluator-0.1.65.dist-info/METADATA
nemo_evaluator-0.1.65.dist-info/WHEEL
nemo_evaluator-0.1.65.dist-info/entry_points.txt
nemo_evaluator-0.1.65.dist-info/top_level.txt
nemo_evaluator-0.1.65.dist-info/RECORD
