Metadata-Version: 2.4
Name: nemo-evaluator
Version: 0.1.65
Summary: Common utilities for NVIDIA evaluation frameworks
Author: NVIDIA
Author-email: nemo-toolkit@nvidia.com
Maintainer: NVIDIA
Maintainer-email: nemo-toolkit@nvidia.com
License:                                  Apache License
Project-URL: homepage, https://github.com/NVIDIA-NeMo/Evaluator
Project-URL: repository, https://github.com/NVIDIA-NeMo/Evaluator/packages/nemo-evaluator
Keywords: deep learning,evaluations,machine learning,gpu,NLP,pytorch,torch
Classifier: Development Status :: 5 - Production/Stable
Classifier: Programming Language :: Python :: 3
Classifier: License :: OSI Approved :: Apache Software License
Classifier: Operating System :: OS Independent
Requires-Python: <3.14,>=3.10
License-File: LICENSE
Requires-Dist: flask
Requires-Dist: jinja2
Requires-Dist: psutil
Requires-Dist: pydantic
Requires-Dist: pydantic-core>=2.17
Requires-Dist: requests
Requires-Dist: structlog
Requires-Dist: typing-extensions>=4.0.0
Requires-Dist: pyyaml
Requires-Dist: werkzeug
Requires-Dist: yq
Dynamic: license-file
